{
    "title": "Тест на понимание темы: контроль доступа",
    "materialType": "test",
    "description": "Проверьте свои знания по теме \"Контроль доступа\"",
    "difficulty": 1,
    "duration": "PT0H5M",
    "tags": {
        "$ref": "../../material-tags.json"
    },
    "skills": {},
    "passingScore": 100,
    "assets": {
        "$ref": "./assets"
    },
    "questions": [
        {
            "question": "Какой компонент AAA отвечает за сбор и представление данных об использовании для целей аудита и выставления счетов?",
            "answerType": "singleChoice",
            "answers": [
                {
                    "answer": "аутентификация",
                    "correct": false,
                    "comment": "Собирает данные и формирует отчеты учет AAA"
                },
                {
                    "answer": "авторизация",
                    "correct": false,
                    "comment": "Собирает данные и формирует отчеты учет AAA"
                },
                {
                    "answer": "учет",
                    "correct": true
                }
            ]
        },
        {
            "question": "Какой компонент AAA отвечает за контроль того, кому разрешен доступ к сети?",
            "answerType": "singleChoice",
            "answers": [
                {
                    "answer": "аутентификация",
                    "correct": true
                },
                {
                    "answer": "авторизация",
                    "correct": false,
                    "comment": "Кому разрешен доступ к сети, контролирует аутентификация"
                },
                {
                    "answer": "учет",
                    "correct": false,
                    "comment": "Кому разрешен доступ к сети, контролирует аутентификация"
                }
            ]
        },
        {
            "question": "Какой компонент AAA отвечает за определение того, к каким ресурсам пользователь может получить доступ?",
            "answerType": "singleChoice",
            "answers": [
                {
                    "answer": "аутентификация",
                    "correct": false,
                    "comment": "К каким ресурсам пользователь имеет доступ, определяет авторизация"
                },
                {
                    "answer": "авторизация",
                    "correct": true
                },
                {
                    "answer": "учет",
                    "correct": false,
                    "comment": "К каким ресурсам пользователь имеет доступ, определяет авторизация"
                }
            ]
        },
        {
            "question": "В реализации 802.1X, какое устройство отвечает за ретрансляцию ответов?",
            "answerType": "singleChoice",
            "answers": [
                {
                    "answer": "запрашивающее устройство",
                    "correct": false,
                    "comment": "В 802.1X аутентификатор, который обычно является коммутатором или беспроводной точкой доступа, отвечает за ретрансляцию сообщений между запрашивающим устройством и сервером аутентификации"
                },
                {
                    "answer": "аутентификатор",
                    "correct": true
                },
                {
                    "answer": "роутер",
                    "correct": false,
                    "comment": "В 802.1X аутентификатор, который обычно является коммутатором или беспроводной точкой доступа, отвечает за ретрансляцию сообщений между запрашивающим устройством и сервером аутентификации"
                },
                {
                    "answer": "сервер аутентификации",
                    "correct": false,
                    "comment": "В 802.1X аутентификатор, который обычно является коммутатором или беспроводной точкой доступа, отвечает за ретрансляцию сообщений между запрашивающим устройством и сервером аутентификации"
                },
                {
                    "answer": "клиент",
                    "correct": false,
                    "comment": "В 802.1X аутентификатор, который обычно является коммутатором или беспроводной точкой доступа, отвечает за ретрансляцию сообщений между запрашивающим устройством и сервером аутентификации"
                }
            ]
        }
    ]
}